configly/__init__.py
configly/client.py
configly/errors.py
configly/version.py
configly_python-1.0.8.dist-info/LICENSE
configly_python-1.0.8.dist-info/METADATA
configly_python-1.0.8.dist-info/WHEEL
configly_python-1.0.8.dist-info/top_level.txt
configly_python-1.0.8.dist-info/RECORD
