Metadata-Version: 2.1
Name: configly-python
Version: 1.0.8
Summary: The Official Python Library for Configly - the modern config/static data key/value store
Home-page: https://github.com/configly/python
Author: Configly
Author-email: configlyco@gmail.com
License: MIT License
Platform: UNKNOWN
Classifier: Programming Language :: Python :: 3
Classifier: License :: OSI Approved :: MIT License
Classifier: Operating System :: OS Independent
Requires-Python: >=3.6
Requires-Dist: requests ; python_version >= "3" and python_version < "4"
